connections_tui/__init__.py
connections_tui-0.0.9.dist-info/METADATA
connections_tui-0.0.9.dist-info/WHEEL
connections_tui-0.0.9.dist-info/entry_points.txt
connections_tui-0.0.9.dist-info/RECORD
