Metadata-Version: 2.4
Name: connections-tui
Version: 0.0.9
Summary: Play NYT Connections in the Terminal with no additional dependencies.
Project-URL: Homepage, https://github.com/mathematicalmichael/connections-tui
Project-URL: Repository, https://github.com/mathematicalmichael/connections-tui.git
Author-email: Michael Pilosov <consistentbayes@gmail.com>
License-Expression: MIT
Keywords: connections,games,nyt,tui
Requires-Python: >=3.8
